main.py
mseep_opcua_mcp-0.1.1.dist-info/licenses/LICENSE
mseep_opcua_mcp-0.1.1.dist-info/METADATA
mseep_opcua_mcp-0.1.1.dist-info/WHEEL
mseep_opcua_mcp-0.1.1.dist-info/entry_points.txt
mseep_opcua_mcp-0.1.1.dist-info/top_level.txt
mseep_opcua_mcp-0.1.1.dist-info/RECORD
