Metadata-Version: 2.4
Name: mseep-opcua-mcp
Version: 0.1.1
Summary: An MCP server that connects AI agents to OPC UA-enabled industrial systems.
Author-email: mseep <support@skydeck.ai>
Requires-Python: >=3.13
License-File: LICENSE
Requires-Dist: cryptography>=45.0.2
Requires-Dist: mcp[cli]>=1.5.0
Requires-Dist: opcua>=0.98.13
Dynamic: license-file
